{
  "hash": "2f9cc9ac",
  "configHash": "6f604422",
  "lockfileHash": "ba7c6388",
  "browserHash": "616ae780",
  "optimized": {
    "vue": {
      "src": "../../../node_modules/vue/dist/vue.runtime.esm-bundler.js",
      "file": "vue.js",
      "fileHash": "c013f65e",
      "needsInterop": false
    },
    "vitepress > @vue/devtools-api": {
      "src": "../../../node_modules/@vue/devtools-api/dist/index.js",
      "file": "vitepress___@vue_devtools-api.js",
      "fileHash": "99876a8a",
      "needsInterop": false
    },
    "vitepress > @vueuse/core": {
      "src": "../../../node_modules/@vueuse/core/index.mjs",
      "file": "vitepress___@vueuse_core.js",
      "fileHash": "11e42e9a",
      "needsInterop": false
    },
    "@astrian/vitepress-plugin-plausible": {
      "src": "../../../node_modules/@astrian/vitepress-plugin-plausible/dist/index.mjs",
      "file": "@astrian_vitepress-plugin-plausible.js",
      "fileHash": "37c1a6b2",
      "needsInterop": false
    }
  },
  "chunks": {
    "chunk-VJWGEPT5": {
      "file": "chunk-VJWGEPT5.js"
    }
  }
}